nixi/__init__.py
nixi/dummy.py
nixa-0.1.0.dist-info/METADATA
nixa-0.1.0.dist-info/WHEEL
nixa-0.1.0.dist-info/top_level.txt
nixa-0.1.0.dist-info/RECORD
